[
{
"fields": {"activity": 1, 
            "date": "2023-04-23", 
            "time": "10:00", 
            "spaces": 25, 
            "location": "Studio A", 
            "running": true},
            "pk": 145039,
            "model": "classbooking_app.session"   
},
{
    "fields": {"activity": 2, 
                "date": "2023-04-23", 
                "time": "11:00", 
                "spaces": 20, 
                "location": "Studio B", 
                "running": true},
                "pk": 245039,
                "model": "classbooking_app.session"   
    },
    {
        "fields": {"activity": 3, 
                    "date": "2023-04-23", 
                    "time": "12:00", 
                    "spaces": 15, 
                    "location": "Studio C", 
                    "running": true},
                    "pk": 345039,
                    "model": "classbooking_app.session"   
        },
        {
            "fields": {"activity": 1, 
                        "date": "2023-04-24", 
                        "time": "10:00", 
                        "spaces": 25, 
                        "location": "Studio A", 
                        "running": true},
                        "pk": 145040,
                        "model": "classbooking_app.session"   
            },
            {
                "fields": {"activity": 2, 
                            "date": "2023-04-24", 
                            "time": "11:00", 
                            "spaces": 20, 
                            "location": "Studio B", 
                            "running": true},
                            "pk": 245040,
                            "model": "classbooking_app.session"   
                },
                {
                    "fields": {"activity": 3, 
                                "date": "2023-04-24", 
                                "time": "12:00", 
                                "spaces": 15, 
                                "location": "Studio C", 
                                "running": true},
                                "pk": 345040,
                                "model": "classbooking_app.session"   
                    }
]
  
